{
  "Alex Tuch": "./audioFiles/Alex_Tuch.mp3",
  "Anders Bjork": "./audioFiles/Anders_Bjork.mp3",
  "Casey Fitzgerald": "./audioFiles/Casey_Fitzgerald.mp3",
  "Casey Mittelstadt": "./audioFiles/Casey_Mittelstadt.mp3",
  "Dylan Cozens": "./audioFiles/Dylan_Cozens.mp3",
  "Henri Jokiharju": "./audioFiles/Henri_Jokiharju.mp3",
  "Ilya Lyubushkin": "./audioFiles/Ilya_Lyubushkin.mp3",
  "Jack Quinn": "./audioFiles/Jack_Quinn.mp3",
  "Jacob Bryson": "./audioFiles/Jacob_Bryson.mp3",
  "Jeff Skinner": "./audioFiles/Jeff_Skinner.mp3",
  "JJ Peterka": "./audioFiles/JJ_Peterka.mp3",
  "Kyle Okposo": "./audioFiles/Kyle_Okposo.mp3",
  "Mattias Samuelsson": "./audioFiles/Mattias_Samuelsson.mp3",
  "Owen Power": "./audioFiles/Owen_Power.mp3",
  "Peyton Krebs": "./audioFiles/Peyton_Krebs.mp3",
  "Rasmus Asplund": "./audioFiles/Rasmus_Asplund.mp3",
  "Rasmus Dahlin": "./audioFiles/Rasmus_Dahlin.mp3",
  "Tage Thompson": "./audioFiles/Tage_Thompson.mp3",
  "Victor Olofsson": "./audioFiles/Victor_Olofsson.mp3",
  "Vinne Hinostroza": "./audioFiles/Vinne_Hinostroza.mp3",
  "Zemgus Girgensons": "./audioFiles/Zemgus_Girgensons.mp3",
  "default": "./audioFiles/default.mp3"
}